[
    {
        "url": "https://raw.githubusercontent.com/EnergizedProtection/block/master/assets/sources/sources.json",
        "filter": "ENERGIZED"
    },
    {
        "url": "https://raw.githubusercontent.com/StevenBlack/hosts/master/readmeData.json",
        "filter": "STEVENBLACK"
    },
    {
        "url": "https://oisd.nl/knownlists.php",
        "filter": "OISD"
    },
    {
        "url": "https://raw.githubusercontent.com/badmojr/1Hosts/master/-data/lists/assets.txt",
        "filter": "1HOSTS"
    }
]